cal/__init__.py
cal/calcultor.py
calculator_test-1.0.4.dev1.dist-info/DESCRIPTION.rst
calculator_test-1.0.4.dev1.dist-info/METADATA
calculator_test-1.0.4.dev1.dist-info/RECORD
calculator_test-1.0.4.dev1.dist-info/WHEEL
calculator_test-1.0.4.dev1.dist-info/metadata.json
calculator_test-1.0.4.dev1.dist-info/top_level.txt
