Metadata-Version: 2.0
Name: calculator-test
Version: 1.0.4.dev1
Summary: A calculator python project
Home-page: https://github.com/cyan-blue/calculator-test
Author: Yan Huang
Author-email: 907790764@qq.com
License: MIT
Keywords: calculator python
Platform: UNKNOWN
Classifier: Development Status :: 4 - Beta
Classifier: Intended Audience :: Developers
Classifier: Topic :: Software Development :: Build Tools
Classifier: License :: OSI Approved :: MIT License
Classifier: Programming Language :: Python :: 2.6
Classifier: Programming Language :: Python :: 2.7
